gpiodmonitor/__init__.py
gpiodmonitor/gpiodmonitor.py
gpiodmonitor-1.3.1.dist-info/LICENSE
gpiodmonitor-1.3.1.dist-info/METADATA
gpiodmonitor-1.3.1.dist-info/WHEEL
gpiodmonitor-1.3.1.dist-info/entry_points.txt
gpiodmonitor-1.3.1.dist-info/top_level.txt
gpiodmonitor-1.3.1.dist-info/RECORD
