Metadata-Version: 2.1
Name: gpiodmonitor
Version: 1.3.1
Author-email: Eike Christian Kühn <eike.kuehn@pixelwoelkchen.de>
Maintainer-email: Eike Christian Kühn <eike.kuehn@pixelwoelkchen.de>
Project-URL: homepage, https://github.com/randomchars42/gpiodmonitor
Project-URL: documentation, https://github.com/randomchars42/gpiodmonitor
Project-URL: source, https://github.com/randomchars42/gpiodmonitor
Project-URL: tracker, https://github.com/randomchars42/gpiodmonitor/issues
Classifier: License :: OSI Approved :: The Unlicense (Unlicense)
Classifier: Programming Language :: Python :: 3
Classifier: Programming Language :: Python :: 3.9
Classifier: Programming Language :: Python :: 3.10
Classifier: Programming Language :: Python :: 3 :: Only
Classifier: Development Status :: 5 - Production/Stable
Classifier: Programming Language :: Python
Requires-Python: >=3.9
License-File: LICENSE
